{"cameraMode":{"drawMode":0,"name":"Shaded","section":"Shading Mode"},"sceneLighting":true,"audioPlay":false,"sceneViewState":{"showFog":true,"showMaterialUpdate":false,"showSkybox":true,"showFlares":true,"showImageEffects":true,"showParticleSystems":true,"showVisualEffectGraphs":true,"m_FxEnabled":true},"in2DMode":false,"pivot":{"x":-19.153696060180665,"y":9.671030044555664,"z":1.2375339269638062},"rotation":{"x":0.1533357948064804,"y":-0.43043577671051028,"z":0.0778399333357811,"w":0.8860561847686768},"size":0.8660253882408142,"orthographic":false}